discordrpc/__init__.py
discordrpc/rpc.py
discordrpc-0.0.0.dist-info/LICENSE.txt
discordrpc-0.0.0.dist-info/METADATA
discordrpc-0.0.0.dist-info/RECORD
discordrpc-0.0.0.dist-info/WHEEL
discordrpc-0.0.0.dist-info/top_level.txt
